quantum_simulator/__init__.py
quantum_simulator/circuits.py
quantum_simulator/gates.py
quantum_simulator/simulator.py
quantum_simulator-0.2.0.dist-info/METADATA
quantum_simulator-0.2.0.dist-info/WHEEL
quantum_simulator-0.2.0.dist-info/entry_points.txt
quantum_simulator-0.2.0.dist-info/licenses/LICENSE
quantum_simulator-0.2.0.dist-info/RECORD
