Metadata-Version: 2.4
Name: quantum-simulator
Version: 0.2.0
Summary: A Python library for simulating quantum computers and quantum algorithms
Project-URL: Homepage, https://github.com/beefy/quantum-simulator
Project-URL: Documentation, https://beefy.github.io/quantum-simulator/
Project-URL: Repository, https://github.com/beefy/quantum-simulator.git
Project-URL: Issues, https://github.com/beefy/quantum-simulator/issues
Project-URL: Changelog, https://github.com/beefy/quantum-simulator/blob/main/CHANGELOG.md
Author-email: Nathaniel Schultz <nate.schultz@outlook.com>
Maintainer-email: Nathaniel Schultz <nate.schultz@outlook.com>
License: Unlicense
License-File: LICENSE
Keywords: computing,quantum,quantum-algorithms,simulation
Classifier: Development Status :: 3 - Alpha
Classifier: Intended Audience :: Developers
Classifier: Intended Audience :: Science/Research
Classifier: License :: Public Domain
Classifier: Operating System :: OS Independent
Classifier: Programming Language :: Python :: 3
Classifier: Programming Language :: Python :: 3.8
Classifier: Programming Language :: Python :: 3.9
Classifier: Programming Language :: Python :: 3.10
Classifier: Programming Language :: Python :: 3.11
Classifier: Programming Language :: Python :: 3.12
Classifier: Topic :: Scientific/Engineering :: Physics
Classifier: Topic :: Software Development :: Libraries :: Python Modules
Requires-Python: >=3.8
Requires-Dist: numpy>=1.20.0
Requires-Dist: scipy>=1.6.0
Provides-Extra: dev
Requires-Dist: black; extra == 'dev'
Requires-Dist: flake8; extra == 'dev'
Requires-Dist: mypy; extra == 'dev'
Requires-Dist: pre-commit; extra == 'dev'
Requires-Dist: pytest-cov; extra == 'dev'
Requires-Dist: pytest>=6.0; extra == 'dev'
Provides-Extra: docs
Requires-Dist: mkdocs-autorefs==1.4.3; extra == 'docs'
Requires-Dist: mkdocs-gen-files==0.6.0; extra == 'docs'
Requires-Dist: mkdocs-literate-nav==0.6.2; extra == 'docs'
Requires-Dist: mkdocs-material==9.7.0; extra == 'docs'
Requires-Dist: mkdocs-section-index==0.3.10; extra == 'docs'
Requires-Dist: mkdocs==1.6.1; extra == 'docs'
Requires-Dist: mkdocstrings[python]==1.0.0; extra == 'docs'
Requires-Dist: pymdown-extensions==10.19.1; extra == 'docs'
Provides-Extra: test
Requires-Dist: pytest-cov; extra == 'test'
Requires-Dist: pytest>=6.0; extra == 'test'
